{"songs":[{"id":"song_1","folder_id":"1Mw4c4kD1av4VufF5x5h3bHKmF96oxI5z","title":"ラメント ~万灯会の夜に~","year":2018,"ensemble_ja":"ピアノ独奏","ensemble_en":"Piano Solo","audio_url":"音源なし","status":"公開","last_updated":"2026-04-11T04:06:08.142Z","comment":"","instruments":[{"code":"instr_1775852350582","parts":1,"name_ja":"ピアノ","name_en":"instr_1775852350582","category_ja":"鍵盤楽器","category_en":"Keyboard","sort_order":1}]},{"id":"song_2","folder_id":"105OwAwskSoXL1lYbkyNB9spCmOZIOaLD","title":"Twinkle Twinkle Little Star Variations(集成)","year":"","ensemble_ja":"","ensemble_en":"","audio_url":"音源なし","status":"公開","last_updated":"2026-04-11T04:06:18.034Z","comment":"","instruments":[]},{"id":"song_3","folder_id":"16xg3L9JfNUSGimxbj4tOlxsJSNBgbASe","title":"パッヘルベルのシャコンヌ(p-trio)","year":"","ensemble_ja":"","ensemble_en":"","audio_url":"音源なし","status":"公開","last_updated":"2026-02-09T09:49:43.769Z","comment":"","instruments":[]},{"id":"song_4","folder_id":"1Hsg7S21L2B0n9LgTaclxHpxbiqckEpnv","title":"トリオ・新アレンジ集","year":"","ensemble_ja":"","ensemble_en":"","audio_url":"音源なし","status":"公開","last_updated":"2026-02-09T09:49:43.769Z","comment":"","instruments":[]},{"id":"song_5","folder_id":"1ZvKdGfiGXZ27Kxb00o0azOCO2BVDMJ7y","title":"二重奏曲「風に…」(2024)最終決定稿","year":"","ensemble_ja":"","ensemble_en":"","audio_url":"https://drive.google.com/file/d/1a1JLuLtddSrJtg4ztTtpO4TY03Vg4Fgx/view?usp=drivesdk|1 風に訊ねよ.mp3\nhttps://drive.google.com/file/d/1ktI9jgiAUZ8-PbnYZo3ODaXKGgsmt9VA/view?usp=drivesdk|II. 風に告げよ.mp3\nhttps://drive.google.com/file/d/1VJNvGUr2z9LENVMmGn9q6yZU1wnf-joZ/view?usp=drivesdk|III. 風に舞う.mp3","status":"公開","last_updated":"2026-04-11T04:40:37.252Z","comment":"1 風に訊ねよ\nII. 風に告げよ\nIII. 風に舞う","instruments":[{"code":"instr_1775852360318","parts":1,"name_ja":"ヴァイオリン","name_en":"instr_1775852360318","category_ja":"弦楽器","category_en":"Strings","sort_order":1},{"code":"instr_1775852366527","parts":1,"name_ja":"チェロ","name_en":"instr_1775852366527","category_ja":"弦楽器","category_en":"Strings","sort_order":2}]},{"id":"song_6","folder_id":"1jbWN7rSkroLIs4OvL67GXv-QW1OtlaBI","title":"Rosamunde","year":"","ensemble_ja":"ピアノ五重奏","ensemble_en":"","audio_url":"https://drive.google.com/file/d/1K5OBzVqe2pKSWYzydOOhbzN2tuddmrKa/view?usp=drivesdk|Rosamunde II.mp3","status":"公開","last_updated":"2026-04-11T03:58:00.990Z","comment":"","instruments":[{"code":"instr_1775852360318","parts":1,"name_ja":"ヴァイオリン","name_en":"instr_1775852360318","category_ja":"弦楽器","category_en":"Strings","sort_order":1},{"code":"instr_1775852363349","parts":1,"name_ja":"ヴィオラ","name_en":"instr_1775852363349","category_ja":"弦楽器","category_en":"Strings","sort_order":2},{"code":"instr_1775852366527","parts":1,"name_ja":"チェロ","name_en":"instr_1775852366527","category_ja":"弦楽器","category_en":"Strings","sort_order":3},{"code":"instr_1775852371103","parts":1,"name_ja":"コントラバス","name_en":"instr_1775852371103","category_ja":"弦楽器","category_en":"Strings","sort_order":4},{"code":"instr_1775852350582","parts":1,"name_ja":"ピアノ","name_en":"instr_1775852350582","category_ja":"鍵盤楽器","category_en":"Keyboard","sort_order":5}]},{"id":"song_7","folder_id":"1n0OgO4PFv2X4dqzn-FpJ51jDLLDPRZMF","title":"さんぽ(トトロ)","year":"","ensemble_ja":"歌+管2弦6","ensemble_en":"","audio_url":"https://drive.google.com/file/d/1xROuUk_b96AJUFTvIbgbaZO6XgipA-Y8/view?usp=drivesdk|さんぽ(full score).mp3","status":"公開","last_updated":"2026-04-11T10:07:44.518Z","comment":"","instruments":[{"code":"Wo_Flute","parts":1,"name_ja":"フルート","name_en":"Flute","category_ja":"木管楽器","category_en":"Woodwind","sort_order":1},{"code":"instr_1775852383708","parts":1,"name_ja":"オーボエ","name_en":"instr_1775852383708","category_ja":"木管楽器","category_en":"Woodwind","sort_order":2},{"code":"instr_1775902007493","parts":1,"name_ja":"ボーカル","name_en":"instr_1775902007493","category_ja":"声","category_en":"Voice","sort_order":3},{"code":"instr_1775852360318","parts":2,"name_ja":"ヴァイオリン","name_en":"instr_1775852360318","category_ja":"弦楽器","category_en":"Strings","sort_order":4},{"code":"instr_1775852363349","parts":1,"name_ja":"ヴィオラ","name_en":"instr_1775852363349","category_ja":"弦楽器","category_en":"Strings","sort_order":5},{"code":"instr_1775852366527","parts":2,"name_ja":"チェロ","name_en":"instr_1775852366527","category_ja":"弦楽器","category_en":"Strings","sort_order":6},{"code":"instr_1775852371103","parts":1,"name_ja":"コントラバス","name_en":"instr_1775852371103","category_ja":"弦楽器","category_en":"Strings","sort_order":7}]},{"id":"song_8","folder_id":"1oGhE8TRp3pI7xrUIsfs0ZbTlwdRetsmn","title":"東京ブギヴギ","year":"","ensemble_ja":"","ensemble_en":"","audio_url":"https://drive.google.com/file/d/1TceCaBHbFK_Gv06aKKrDPt-kvK89dgV4/view?usp=drivesdk|東京ブギヴギ.mp3","status":"公開","last_updated":"2026-04-11T04:41:37.488Z","comment":"","instruments":[{"code":"Wo_Flute","parts":1,"name_ja":"フルート","name_en":"Flute","category_ja":"木管楽器","category_en":"Woodwind","sort_order":1},{"code":"instr_1775852360318","parts":1,"name_ja":"ヴァイオリン","name_en":"instr_1775852360318","category_ja":"弦楽器","category_en":"Strings","sort_order":2},{"code":"instr_1775852363349","parts":1,"name_ja":"ヴィオラ","name_en":"instr_1775852363349","category_ja":"弦楽器","category_en":"Strings","sort_order":3}]},{"id":"song_10","folder_id":"1vMfmzq_hO5glFq8GhZgt8YTA7-GNkBzr","title":"ユーフォニアムとピアノ","year":"","ensemble_ja":"","ensemble_en":"","audio_url":"音源なし","status":"公開","last_updated":"2025-02-28T01:24:56.362Z","comment":"","instruments":[]},{"id":"song_11","folder_id":"18Kt_V_AHvw3y8ZqdVlabQQGIbwVOoijP","title":"ドイツの子供の歌によるパラフレーズ","year":2019,"ensemble_ja":"オーケストラ","ensemble_en":"","audio_url":"https://drive.google.com/file/d/1aKHfX6M2y97B92NwNyDH8gnWZOCffMxr/view?usp=drivesdk|ドイツの子供の歌パラフレーズ.mp3","status":"公開","last_updated":"2026-04-11T04:46:33.143Z","comment":"","instruments":[{"code":"Wo_Flute","parts":1,"name_ja":"フルート","name_en":"Flute","category_ja":"木管楽器","category_en":"Woodwind","sort_order":1},{"code":"instr_1775852398839","parts":1,"name_ja":"ピッコロ","name_en":"instr_1775852398839","category_ja":"木管楽器","category_en":"Woodwind","sort_order":2},{"code":"instr_1775852383708","parts":1,"name_ja":"オーボエ","name_en":"instr_1775852383708","category_ja":"木管楽器","category_en":"Woodwind","sort_order":3},{"code":"instr_1775852413715","parts":2,"name_ja":"クラリネット","name_en":"instr_1775852413715","category_ja":"木管楽器","category_en":"Woodwind","sort_order":4},{"code":"instr_1775852430598","parts":2,"name_ja":"ファゴット","name_en":"instr_1775852430598","category_ja":"木管楽器","category_en":"Woodwind","sort_order":5},{"code":"instr_1775852512629","parts":2,"name_ja":"フレンチホルン","name_en":"instr_1775852512629","category_ja":"金管楽器","category_en":"Brass","sort_order":6},{"code":"instr_1775852492636","parts":1,"name_ja":"トランペット","name_en":"instr_1775852492636","category_ja":"金管楽器","category_en":"Brass","sort_order":7},{"code":"instr_1775882669434","parts":1,"name_ja":"ハープシコード","name_en":"instr_1775882669434","category_ja":"鍵盤楽器","category_en":"Keyboard","sort_order":8},{"code":"instr_1775852360318","parts":2,"name_ja":"ヴァイオリン","name_en":"instr_1775852360318","category_ja":"弦楽器","category_en":"Strings","sort_order":9},{"code":"instr_1775852363349","parts":1,"name_ja":"ヴィオラ","name_en":"instr_1775852363349","category_ja":"弦楽器","category_en":"Strings","sort_order":10},{"code":"instr_1775852366527","parts":1,"name_ja":"チェロ","name_en":"instr_1775852366527","category_ja":"弦楽器","category_en":"Strings","sort_order":11},{"code":"instr_1775852371103","parts":1,"name_ja":"コントラバス","name_en":"instr_1775852371103","category_ja":"弦楽器","category_en":"Strings","sort_order":12}]},{"id":"song_12","folder_id":"10xugAC2mzb2RyhPCiMxt9wiHRv-eWblO","title":"Paraphrase über ”Schweizer kinder-lieds”","year":"","ensemble_ja":"","ensemble_en":"","audio_url":"音源なし","status":"公開","last_updated":"2025-02-18T14:14:51.074Z","comment":"","instruments":[]},{"id":"song_13","folder_id":"1FafsSV2YyxLEUdW9JXxfu0MfgqXBi4bV","title":"こどものうたメドレー","year":"","ensemble_ja":"","ensemble_en":"","audio_url":"音源なし","status":"公開","last_updated":"2025-02-18T14:14:51.074Z","comment":"","instruments":[]},{"id":"song_14","folder_id":"1Rj82H_6bmbp-H6g9ru5xrQNnQ9RR_Hwx","title":"00組曲「鎌倉の四季」完成品","year":"","ensemble_ja":"","ensemble_en":"","audio_url":"音源なし","status":"公開","last_updated":"2025-02-18T14:14:51.074Z","comment":"","instruments":[]},{"id":"song_15","folder_id":"1SdtiiWlY5ZmFxGE-EEAR7vPglgI2OQ6-","title":"So-Ran Fantasie(ピアノ連弾)","year":2018,"ensemble_ja":"","ensemble_en":"","audio_url":"音源なし","status":"公開","last_updated":"2026-04-11T04:48:58.414Z","comment":"","instruments":[{"code":"instr_1775852350582","parts":2,"name_ja":"ピアノ","name_en":"instr_1775852350582","category_ja":"鍵盤楽器","category_en":"Keyboard","sort_order":1}]},{"id":"song_16","folder_id":"1fqyq5p23IHJnS164MBzVYgkZYrcIai3X","title":"ダッシュ！","year":"","ensemble_ja":"","ensemble_en":"","audio_url":"音源なし","status":"公開","last_updated":"2026-04-11T04:51:13.614Z","comment":"","instruments":[{"code":"instr_1775852438406","parts":1,"name_ja":"ソプラノサックス","name_en":"instr_1775852438406","category_ja":"木管楽器","category_en":"Woodwind","sort_order":1},{"code":"instr_1775852448232","parts":1,"name_ja":"アルトサックス","name_en":"instr_1775852448232","category_ja":"木管楽器","category_en":"Woodwind","sort_order":2},{"code":"instr_1775852454525","parts":1,"name_ja":"テナーサックス","name_en":"instr_1775852454525","category_ja":"木管楽器","category_en":"Woodwind","sort_order":3},{"code":"instr_1775852459646","parts":1,"name_ja":"バリトンサックス","name_en":"instr_1775852459646","category_ja":"木管楽器","category_en":"Woodwind","sort_order":4}]},{"id":"song_17","folder_id":"1hgp00ZXk-wrZ__iRJdyKHOo9hzYghqik","title":"河内長野市民のためのオーケストラ・ファンファーレ","year":"","ensemble_ja":"","ensemble_en":"","audio_url":"音源なし","status":"公開","last_updated":"2025-02-18T14:14:51.074Z","comment":"","instruments":[]},{"id":"song_18","folder_id":"1pSF-c0dNeBozuWfjhKbvl0upR-n2Oi6O","title":"ブラームス ピアノ協奏曲第2番より","year":"","ensemble_ja":"","ensemble_en":"","audio_url":"音源なし","status":"公開","last_updated":"2025-02-18T14:14:51.074Z","comment":"","instruments":[]},{"id":"song_19","folder_id":"1wJNeM9VLUxLB50J83JaOmpboI9NT72Z5","title":"チェロとピアノ「街道を行く」","year":"","ensemble_ja":"","ensemble_en":"","audio_url":"音源なし","status":"公開","last_updated":"2025-02-18T14:14:51.074Z","comment":"","instruments":[]},{"id":"song_20","folder_id":"1yN4sZC_aDKHHwJVZrxSnZ_jS3zNfCbBY","title":"TANGESSIVO改訂版(弦４)","year":"","ensemble_ja":"","ensemble_en":"","audio_url":"音源なし","status":"公開","last_updated":"2025-02-18T14:14:51.074Z","comment":"","instruments":[]},{"id":"song_21","folder_id":"1vrk1AJJy7UvdxzCkULm8aj5POqqLvE2X","title":"02奥河内幻想(決定稿)","year":"","ensemble_ja":"","ensemble_en":"","audio_url":"音源なし","status":"公開","last_updated":"2025-02-18T14:14:50.255Z","comment":"","instruments":[]},{"id":"song_22","folder_id":"17nvZ40CJyO5EvNhLfMxnuzRrMWJ2gEyo","title":"00楠公首塚に寄せる七つの幻想","year":"","ensemble_ja":"","ensemble_en":"","audio_url":"音源なし","status":"公開","last_updated":"2025-02-18T14:14:49.578Z","comment":"","instruments":[]},{"id":"song_23","folder_id":"1OYi04v9YWMzg6AR-cFIX0eEkgYcnSQzf","title":"二胡とヴァイオリンのための三つの小品pdf","year":"","ensemble_ja":"","ensemble_en":"","audio_url":"https://drive.google.com/file/d/1AWdF2gm7OvSuwoScmwUhiIUmfh4pC5VO/view?usp=drivesdk|風に舞う(二胡+vn).mp3\nhttps://drive.google.com/file/d/1T8tUdM5RInrg_UTWbfAqkjYkZsgjwvBg/view?usp=drivesdk|風の歌duo(vn+zhon).mp3\nhttps://drive.google.com/file/d/1Vv8BIBE_Ye0xCnqePiIS1RU-BDQNeET7/view?usp=drivesdk|風薫る(vn+二胡).mp3","status":"公開","last_updated":"2026-04-14T11:12:10.957Z","comment":"","instruments":[]},{"id":"song_24","folder_id":"1PRG-_gzi_4p4TAfUhULfDF0DLysVPgPw","title":"金と銀SAXオケ・パート譜","year":"","ensemble_ja":"","ensemble_en":"","audio_url":"音源なし","status":"公開","last_updated":"2025-02-18T14:14:49.578Z","comment":"","instruments":[]},{"id":"song_25","folder_id":"1XNXO6-alCv_lx4zwWzfVM5VONCELbiZR","title":"Prokofiev","year":"","ensemble_ja":"","ensemble_en":"","audio_url":"音源なし","status":"公開","last_updated":"2025-02-18T14:14:49.578Z","comment":"","instruments":[]},{"id":"song_26","folder_id":"1eUOCmk9TLXnA4au8LM4B78TNwlDV84G3","title":"三点セット","year":"","ensemble_ja":"","ensemble_en":"","audio_url":"音源なし","status":"公開","last_updated":"2025-02-18T14:14:49.578Z","comment":"","instruments":[]},{"id":"song_27","folder_id":"1l5OrUeooo1MwPJw6OXbZ5Y-2gPrYjY68","title":"組曲「紺碧の海へ」(2014)三重奏版","year":"","ensemble_ja":"","ensemble_en":"","audio_url":"音源なし","status":"公開","last_updated":"2025-02-18T14:14:49.578Z","comment":"","instruments":[]},{"id":"song_28","folder_id":"1mbnbh2v8cnN1bGPJu2Z61pcRE5UPWsxs","title":"Sonata","year":2015,"ensemble_ja":"テナーサックスとピアノ","ensemble_en":"","audio_url":"https://drive.google.com/file/d/1T3LTkjq2rZ7MxidiCc2EXhyQG-ZaXyyp/view?usp=drivesdk|第1楽章 風天(音域改訂版).mp3\nhttps://drive.google.com/file/d/1EZkxrmaHbxvUf6V6JsFuv-VvJgZ8Fees/view?usp=drivesdk|第２楽章Aria.mp3\nhttps://drive.google.com/file/d/1c6qXLN8Bn9M1dmkAqvDjwoNXr2IfIHEj/view?usp=drivesdk|第３楽章「鳴神」(決定稿).mp3","status":"公開","last_updated":"2026-04-11T05:28:00.313Z","comment":"第1楽章 風天\n第２楽章 薫風\n第３楽章 鳴神\n\n　この曲は、テナー・サクソフォンとピアノのために書かれた３楽章からなるソナタである。\n\n　第１楽章は伝統的なソナタ形式を用いている。この形式で書くのは、10年ほど前に書き、チューリッヒのトーンハレで津田理子さんにゆり初演され、好評を得たピアノのためのソナチネ以来のことであり、また、二度と書くことはあるまいと思っていたものだったが、伊藤君の依頼を聞きながら、私の作風から離れていったこの西洋の形式にもう一度戻って、自分なりの世界を描いてみようと思ったのが作曲のきっかけであった。\n　終楽章にトッカータ風の楽章を持って来たが、それもかつてのソナチネと同様である。\n　各楽章にタイトルをつけているが、全曲を通してあるストーリーがあるわけではない。\n　ただ、江戸時代初期の俵屋宗達による風神雷神の絵をもとに、第１楽章に風神を意味する「風天」というタイトルを、第３楽章には雷神を意味する「鳴神」というタイトルをつけた。\n　間の第２楽章はあまり関係のない「薫風」というタイトルにしたが、明確な調性を持つアリアのような楽章を間に挟んだ、急緩急の古典的な構成をとろうと思ったためである。\n　第１楽章はとても早く出来てしまったけれど、次にとりかかった終楽章が、なかなか出来ず、何度も書き直しし、ようやくこの形に落ち着いた。第３楽章の中間においた２楽章の回想は、計画通りだったが、あまりに遅々としてすすまないために、先に２楽章を書き始めると、こちらの方が先に出来上がってしまった。\n終楽章は、単純な作品ではあるが、意外と難産だった。\n　それ故かどうかわからないが、作者として、とても思い入れの強い作品となった。お聞き下さる皆様の気に入っていただければ幸甚である。\n\n　　　　　　　　　　　　　　　　　　　　　　　　　2016年4月28日 作曲者","instruments":[]},{"id":"song_29","folder_id":"1o3n83VdnbVQyYyNK5xHW-IK9Wi2VirZC","title":"岩湧の四季","year":"","ensemble_ja":"","ensemble_en":"","audio_url":"音源なし","status":"公開","last_updated":"2025-02-18T14:14:49.578Z","comment":"","instruments":[]},{"id":"song_30","folder_id":"1u_i4TIK16SFSBFpmOtR6MlSo3N1lDSrp","title":"鎌倉小景二題","year":"","ensemble_ja":"","ensemble_en":"","audio_url":"https://drive.google.com/file/d/1zn6FJa5ky33s-W_58jYIkwhl7OIt56MD/view?usp=drivesdk|徳備 康純_鎌倉小景二題 (2018) 第１曲 ゆふぐれて、時雨さそふ化粧坂.mp3\nhttps://drive.google.com/file/d/1NE3CRfFt3JIl9GgQEhhHuKBOROsOYaQi/view?usp=drivesdk|徳備 康純_鎌倉小景二題 (2018) 第２曲 ラメント ～万灯会の夜に～.mp3","status":"公開","last_updated":"2026-04-11T03:59:28.485Z","comment":"","instruments":[]},{"id":"song_31","folder_id":"15kSojCV0ayyX3vka_d39rinMuBOSoImt","title":"Nessun dorma!","year":"","ensemble_ja":"","ensemble_en":"","audio_url":"音源なし","status":"公開","last_updated":"2025-02-18T14:14:48.559Z","comment":"","instruments":[]},{"id":"song_32","folder_id":"1_N9LH68OA3U7FvMi4HMzDLCT23_4b9De","title":"OIWAKE","year":"","ensemble_ja":"","ensemble_en":"","audio_url":"音源なし","status":"公開","last_updated":"2025-02-18T14:14:48.559Z","comment":"","instruments":[]},{"id":"song_33","folder_id":"1gEoLtCdLVTJ9c8pUpTnJHaLFXextNGHP","title":"Moon river","year":"","ensemble_ja":"","ensemble_en":"","audio_url":"音源なし","status":"公開","last_updated":"2025-02-18T14:14:48.559Z","comment":"","instruments":[]},{"id":"song_34","folder_id":"1kkxoNbbzal_etBDztfIfvciWKcFfX20Y","title":"Jesus bleibet meine Freude","year":"","ensemble_ja":"","ensemble_en":"","audio_url":"https://drive.google.com/file/d/1M5fvUdS7lMuDLnGRDUnk-WuUx6MTQ4Wa/view?usp=drivesdk|Jesus bleibet meine Freude.mp3","status":"公開","last_updated":"2026-04-11T03:59:44.494Z","comment":"","instruments":[]},{"id":"song_35","folder_id":"1r-H5JTwfKN3k1iXGoJkd4ys7kSqpWOVi","title":"00街道を行く第２番","year":"","ensemble_ja":"","ensemble_en":"","audio_url":"音源なし","status":"公開","last_updated":"2025-02-18T14:14:48.559Z","comment":"","instruments":[]},{"id":"song_36","folder_id":"1sHx6nzcbZAF6O8gmNXWTMak6jVPGx7lb","title":"風に舞う","year":"","ensemble_ja":"","ensemble_en":"","audio_url":"https://drive.google.com/file/d/1ot7xFcfSmGLv0lF9iAs4T7csViFnSgkA/view?usp=drivesdk|Ballo nel vento.mp3","status":"公開","last_updated":"2026-04-11T03:59:58.924Z","comment":"","instruments":[]},{"id":"song_37","folder_id":"1tH-xVdEupc3CJgDnlmM_91A9pKCYHrND","title":"鎌倉、路の風景より(2019)","year":"","ensemble_ja":"","ensemble_en":"","audio_url":"音源なし","status":"公開","last_updated":"2025-02-18T14:14:48.559Z","comment":"","instruments":[]},{"id":"song_38","folder_id":"1x52EW9WY3j8djKvnr2329vFkm0WGvgjR","title":"OSAKA Symphonette (2017)","year":"","ensemble_ja":"","ensemble_en":"","audio_url":"音源なし","status":"公開","last_updated":"2025-02-18T14:14:48.559Z","comment":"","instruments":[]},{"id":"song_39","folder_id":"1ztzmxEP5xwlaMDGjdF28u-Bj0v33jP5i","title":"木管五重奏のための三つの性格的小品","year":2018,"ensemble_ja":"木管五重奏","ensemble_en":"","audio_url":"https://drive.google.com/file/d/1vNmTJCULmY6jjqlXLE7wdz5Qh5FLolOz/view?usp=drivesdk|徳備 康純_木管五重奏のための三つの性格的小品(2018) 第１曲 こどもみこしねり歩く (前奏曲).mp3\nhttps://drive.google.com/file/d/1DexxsbHX5uSGQqfJisktyvZicYfoApSd/view?usp=drivesdk|徳備 康純_木管五重奏のための三つの性格的小品(2018) 第２曲 穏やかな語らい (間奏曲).mp3\nhttps://drive.google.com/file/d/1ge4gkg041U1OzfHKFQfySQGQN7h-7wUt/view?usp=drivesdk|徳備 康純_木管五重奏のための三つの性格的小品(2018) 第３曲 かけっこ (常動曲).mp3","status":"公開","last_updated":"2026-04-11T05:31:53.578Z","comment":"第1曲 こどもみこしねり歩く (前奏曲)\n第2曲 穏やかな語らい (間奏曲)\n第3曲 かけっこ (常動曲)","instruments":[{"code":"Wo_Flute","parts":1,"name_ja":"フルート","name_en":"Flute","category_ja":"木管楽器","category_en":"Woodwind","sort_order":1},{"code":"instr_1775852383708","parts":1,"name_ja":"オーボエ","name_en":"instr_1775852383708","category_ja":"木管楽器","category_en":"Woodwind","sort_order":2},{"code":"instr_1775852413715","parts":1,"name_ja":"クラリネット","name_en":"instr_1775852413715","category_ja":"木管楽器","category_en":"Woodwind","sort_order":3},{"code":"instr_1775852512629","parts":1,"name_ja":"フレンチホルン","name_en":"instr_1775852512629","category_ja":"金管楽器","category_en":"Brass","sort_order":4},{"code":"instr_1775852430598","parts":1,"name_ja":"ファゴット","name_en":"instr_1775852430598","category_ja":"木管楽器","category_en":"Woodwind","sort_order":5}]},{"id":"song_1775902691140_eaajg","folder_id":"1epz7Z6kllQu524erg7dr9UcjQHazSxMH","title":"ロマの幻想","year":"","ensemble_ja":"ユーフォニアム＋ピアノ","ensemble_en":"","audio_url":"音源なし","status":"公開","last_updated":"2026-04-11T10:20:12.657Z","comment":"","instruments":[{"code":"instr_1775852528937","parts":1,"name_ja":"ユーフォニアム","name_en":"instr_1775852528937","category_ja":"金管楽器","category_en":"Brass","sort_order":1},{"code":"instr_1775852350582","parts":1,"name_ja":"ピアノ","name_en":"instr_1775852350582","category_ja":"鍵盤楽器","category_en":"Keyboard","sort_order":2}]},{"id":"song_1775902691140_s3c5t","folder_id":"1mwWzFNXAJTTIcWn0G_xl9UJAw9Wb9WaL","title":"道化師の夢 -The Clown's dream-","year":"","ensemble_ja":"ユーフォニアム＋ピアノ","ensemble_en":"","audio_url":"音源なし","status":"公開","last_updated":"2026-04-11T10:21:14.627Z","comment":"","instruments":[{"code":"instr_1775852528937","parts":1,"name_ja":"ユーフォニアム","name_en":"instr_1775852528937","category_ja":"金管楽器","category_en":"Brass","sort_order":1},{"code":"instr_1775852350582","parts":1,"name_ja":"ピアノ","name_en":"instr_1775852350582","category_ja":"鍵盤楽器","category_en":"Keyboard","sort_order":2}]},{"id":"song_1775902691140_zoup3","folder_id":"1Uw2lPmveTKWYV4SZ61filzp84W37UV2V","title":"組曲「サーカス」 Suite \"Circus\"","year":"","ensemble_ja":"ユーフォニアム四重奏","ensemble_en":"Euphonium Quartet","audio_url":"音源なし","status":"公開","last_updated":"2026-04-11T10:23:00.378Z","comment":"","instruments":[{"code":"instr_1775852528937","parts":4,"name_ja":"ユーフォニアム","name_en":"instr_1775852528937","category_ja":"金管楽器","category_en":"Brass","sort_order":1}]}],"master":{"categories":[{"id":"Vo","name_ja":"声","name_en":"Voice","sort_order":1},{"id":"Pf","name_ja":"鍵盤楽器","name_en":"Keyboard","sort_order":2},{"id":"St","name_ja":"弦楽器","name_en":"Strings","sort_order":3},{"id":"Wo","name_ja":"木管楽器","name_en":"Woodwind","sort_order":4},{"id":"Br","name_ja":"金管楽器","name_en":"Brass","sort_order":5},{"id":"Pe","name_ja":"打楽器","name_en":"Percussion","sort_order":6},{"id":"Ot","name_ja":"その他","name_en":"Other","sort_order":7}],"instruments":[{"code":"instr_1775852326716","category_id":"Vo","name_ja":"ソプラノ","name_en":"","sort_order":1},{"code":"instr_1775852330141","category_id":"Vo","name_ja":"アルト","name_en":"","sort_order":2},{"code":"instr_1775852332802","category_id":"Vo","name_ja":"テノール","name_en":"","sort_order":3},{"code":"instr_1775852502646","category_id":"Br","name_ja":"コルネット","name_en":"","sort_order":3},{"code":"instr_1775882669434","category_id":"Pf","name_ja":"ハープシコード","name_en":"","sort_order":3},{"code":"instr_1775852341316","category_id":"Vo","name_ja":"バリトン","name_en":"","sort_order":4},{"code":"instr_1775852506127","category_id":"Br","name_ja":"フリューゲルホーン","name_en":"","sort_order":4},{"code":"instr_1775852344442","category_id":"Vo","name_ja":"バス","name_en":"","sort_order":5},{"code":"instr_1775852512629","category_id":"Br","name_ja":"フレンチホルン","name_en":"","sort_order":5},{"code":"instr_1775852350582","category_id":"Pf","name_ja":"ピアノ","name_en":"","sort_order":6},{"code":"instr_1775852521863","category_id":"Br","name_ja":"トロンボーン","name_en":"","sort_order":6},{"code":"instr_1775902007493","category_id":"Vo","name_ja":"ボーカル","name_en":"","sort_order":6},{"code":"instr_1775852353396","category_id":"Pf","name_ja":"チェレスタ","name_en":"","sort_order":7},{"code":"instr_1775852525154","category_id":"Br","name_ja":"バストロンボーン","name_en":"","sort_order":7},{"code":"instr_1775852360318","category_id":"St","name_ja":"ヴァイオリン","name_en":"","sort_order":8},{"code":"instr_1775852528937","category_id":"Br","name_ja":"ユーフォニアム","name_en":"","sort_order":8},{"code":"instr_1775852363349","category_id":"St","name_ja":"ヴィオラ","name_en":"","sort_order":9},{"code":"instr_1775852533513","category_id":"Br","name_ja":"チューバ","name_en":"","sort_order":9},{"code":"instr_1775852366527","category_id":"St","name_ja":"チェロ","name_en":"","sort_order":10},{"code":"instr_1775852371103","category_id":"St","name_ja":"コントラバス","name_en":"","sort_order":11},{"code":"instr_1775852383708","category_id":"Wo","name_ja":"オーボエ","name_en":"","sort_order":12},{"code":"instr_1775852388102","category_id":"Wo","name_ja":"イングリッシュホルン","name_en":"","sort_order":13},{"code":"instr_1775852398839","category_id":"Wo","name_ja":"ピッコロ","name_en":"","sort_order":14},{"code":"Wo_Flute","category_id":"Wo","name_ja":"フルート","name_en":"Flute","sort_order":15},{"code":"instr_1775852413715","category_id":"Wo","name_ja":"クラリネット","name_en":"","sort_order":16},{"code":"instr_1775852471636","category_id":"Wo","name_ja":"アルトクラリネット","name_en":"","sort_order":17},{"code":"instr_1775852479558","category_id":"Wo","name_ja":"バスクラリネット","name_en":"","sort_order":18},{"code":"instr_1775852430598","category_id":"Wo","name_ja":"ファゴット","name_en":"","sort_order":19},{"code":"instr_1775852438406","category_id":"Wo","name_ja":"ソプラノサックス","name_en":"","sort_order":20},{"code":"instr_1775852448232","category_id":"Wo","name_ja":"アルトサックス","name_en":"","sort_order":21},{"code":"instr_1775852454525","category_id":"Wo","name_ja":"テナーサックス","name_en":"","sort_order":22},{"code":"instr_1775852459646","category_id":"Wo","name_ja":"バリトンサックス","name_en":"","sort_order":23},{"code":"instr_1775852464300","category_id":"Wo","name_ja":"バスサックス","name_en":"","sort_order":24},{"code":"instr_1775852496546","category_id":"Br","name_ja":"ピッコロトランペット","name_en":"","sort_order":25},{"code":"instr_1775852492636","category_id":"Br","name_ja":"トランペット","name_en":"","sort_order":26}]},"updatedAt":"2026-04-14T11:12:16.580Z"}